llama_index/tools/desearch/__init__.py
llama_index/tools/desearch/base.py
llama_index_tools_desearch-0.1.1.dist-info/METADATA
llama_index_tools_desearch-0.1.1.dist-info/WHEEL
llama_index_tools_desearch-0.1.1.dist-info/licenses/LICENSE
llama_index_tools_desearch-0.1.1.dist-info/RECORD
