Metadata-Version: 2.4
Name: llama-index-tools-desearch
Version: 0.1.1
Summary: llama-index tools desearch integration
Author-email: Desearch <support@desearch.com>
Maintainer-email: Desearch <support@desearch.com>
License-Expression: MIT
License-File: LICENSE
Requires-Python: <4.0,>=3.10
Requires-Dist: desearch-py>=1.0.0
Requires-Dist: llama-index-core<0.13,>=0.12.0
Requires-Dist: openai
